vifapi/App.py
vifapi/ChildPath.py
vifapi/Router.py
vifapi/__init__.py
vifapi/default_options.py
vifapi/py.typed
vifapi-0.0.4.dist-info/METADATA
vifapi-0.0.4.dist-info/WHEEL
vifapi-0.0.4.dist-info/licenses/LICENSE.txt
vifapi-0.0.4.dist-info/RECORD
